odoo/addons/sale_stock_delivery_address/README.rst
odoo/addons/sale_stock_delivery_address/__init__.py
odoo/addons/sale_stock_delivery_address/__manifest__.py
odoo/addons/sale_stock_delivery_address/i18n/ca.po
odoo/addons/sale_stock_delivery_address/i18n/es.po
odoo/addons/sale_stock_delivery_address/i18n/sale_stock_delivery_address.pot
odoo/addons/sale_stock_delivery_address/models/__init__.py
odoo/addons/sale_stock_delivery_address/models/procurement_group.py
odoo/addons/sale_stock_delivery_address/models/sale_order.py
odoo/addons/sale_stock_delivery_address/models/sale_order_line.py
odoo/addons/sale_stock_delivery_address/readme/CONTRIBUTORS.rst
odoo/addons/sale_stock_delivery_address/readme/DESCRIPTION.rst
odoo/addons/sale_stock_delivery_address/readme/USAGE.rst
odoo/addons/sale_stock_delivery_address/static/description/icon.png
odoo/addons/sale_stock_delivery_address/static/description/index.html
odoo/addons/sale_stock_delivery_address/tests/__init__.py
odoo/addons/sale_stock_delivery_address/tests/test_sale_stock_delivery_address.py
odoo/addons/sale_stock_delivery_address/views/res_partner_view.xml
odoo/addons/sale_stock_delivery_address/views/sale_order_view.xml
odoo13_addon_sale_stock_delivery_address-13.0.1.0.4.dist-info/METADATA
odoo13_addon_sale_stock_delivery_address-13.0.1.0.4.dist-info/WHEEL
odoo13_addon_sale_stock_delivery_address-13.0.1.0.4.dist-info/top_level.txt
odoo13_addon_sale_stock_delivery_address-13.0.1.0.4.dist-info/RECORD
